bw2speedups/__init__.py
bw2speedups/_consolidate.cp37-win32.pyd
bw2speedups/_find_first.cp37-win32.pyd
bw2speedups/_indexer.cp37-win32.pyd
bw2speedups-2.4.dist-info/LICENSE
bw2speedups-2.4.dist-info/METADATA
bw2speedups-2.4.dist-info/WHEEL
bw2speedups-2.4.dist-info/top_level.txt
bw2speedups-2.4.dist-info/RECORD
