Metadata-Version: 2.1
Name: bw2speedups
Version: 2.4
Summary: Cython functions to speed up Brightway2 LCA calculations
Home-page: https://github.com/brightway-lca/brightway2-speedups
Author: Chris Mutel
Author-email: cmutel@gmail.com
Classifier: Development Status :: 5 - Production/Stable
Classifier: Intended Audience :: Developers
Classifier: License :: OSI Approved :: BSD License
Classifier: Operating System :: MacOS :: MacOS X
Classifier: Operating System :: Microsoft :: Windows
Classifier: Operating System :: POSIX
Classifier: Programming Language :: Python
Classifier: Programming Language :: Python :: 3
License-File: LICENSE
